Activeconnect/__init__.py
Activeconnect/authentication_api.py
Activeconnect/authentication_method.py
Activeconnect/config.py
Activeconnect/hmac.py
Activeconnect/management_api.py
Activeconnect/session.py
Activeconnect/status.py
Activeconnect-0.0.8.dist-info/LICENSE
Activeconnect-0.0.8.dist-info/METADATA
Activeconnect-0.0.8.dist-info/WHEEL
Activeconnect-0.0.8.dist-info/top_level.txt
Activeconnect-0.0.8.dist-info/RECORD
