Metadata-Version: 2.1
Name: Activeconnect
Version: 0.0.8
Summary: Python package to access Activeconnect API
Home-page: UNKNOWN
Author: Activeconnect
Author-email: support@activeconnect.io
License: UNKNOWN
Platform: UNKNOWN
Classifier: Programming Language :: Python :: 3
Classifier: License :: OSI Approved :: MIT License
Classifier: Operating System :: OS Independent
Requires-Python: >=3.6
Requires-Dist: marshmallow-dataclass
Requires-Dist: marshmallow-enum
